SGfunniest/_init_.py
SGfunniest/text.py
SGfunniest-0.1.9.dist-info/METADATA
SGfunniest-0.1.9.dist-info/WHEEL
SGfunniest-0.1.9.dist-info/top_level.txt
SGfunniest-0.1.9.dist-info/RECORD
